mktdt.py
market_datetime-0.0.1.dist-info/METADATA
market_datetime-0.0.1.dist-info/WHEEL
market_datetime-0.0.1.dist-info/top_level.txt
market_datetime-0.0.1.dist-info/RECORD
